stringthings/__init__.py
stringthings/compression.py
stringthings/dates.py
stringthings/errors.py
stringthings/filenames.py
stringthings/numbers.py
stringthings/splits.py
stringthings-0.2.9.dist-info/licenses/LICENSE
stringthings-0.2.9.dist-info/METADATA
stringthings-0.2.9.dist-info/WHEEL
stringthings-0.2.9.dist-info/top_level.txt
stringthings-0.2.9.dist-info/RECORD
