Metadata-Version: 2.4
Name: stringthings
Version: 0.2.9
Summary: some functions to work with strings.
Author-email: Martin Carlos Araya <martinaraya@gmail.com>
License: MIT License
Project-URL: Homepage, https://github.com/ayaranitram/stringthings
Project-URL: Bug Tracker, https://github.com/ayaranitram/stringthings/issues
Classifier: Programming Language :: Python :: 3.7
Classifier: Programming Language :: Python :: 3.8
Classifier: Programming Language :: Python :: 3.9
Classifier: Programming Language :: Python :: 3.10
Classifier: Programming Language :: Python :: 3.11
Classifier: License :: OSI Approved :: MIT License
Classifier: Operating System :: OS Independent
Requires-Python: >=3.7
License-File: LICENSE
Requires-Dist: numpy
Requires-Dist: pandas
Dynamic: license-file
